pylie/LieGroup.py
pylie/MR1.py
pylie/O1_2.py
pylie/Quaternion.py
pylie/R3.py
pylie/SE2.py
pylie/SE23.py
pylie/SE3.py
pylie/SIM3.py
pylie/SL2.py
pylie/SO3.py
pylie/SOT3.py
pylie/Trajectory.py
pylie/__init__.py
pylie/analysis.py
pylie/plotting.py
pylieg-0.2.3.dist-info/licenses/LICENSE
pylieg-0.2.3.dist-info/METADATA
pylieg-0.2.3.dist-info/WHEEL
pylieg-0.2.3.dist-info/top_level.txt
pylieg-0.2.3.dist-info/RECORD
