Metadata-Version: 2.4
Name: pylieg
Version: 0.2.3
Summary: Lie groups in Python
Author-email: Pieter van Goor <p.c.h.vangoor@utwente.nl>
License:                     GNU GENERAL PUBLIC LICENSE
Project-URL: Homepage, https://github.com/pvangoor/pylie
Project-URL: Issues, https://github.com/pvangoor/pylie/issues
Keywords: Lie,Lie group,Lie algebra,matrix,manifold,geometry,symmetry,group
Classifier: Programming Language :: Python :: 3
Classifier: License :: OSI Approved :: GNU General Public License v3 (GPLv3)
Classifier: Operating System :: OS Independent
Requires-Python: >=3.6
License-File: LICENSE
Requires-Dist: numpy
Requires-Dist: scipy
Requires-Dist: matplotlib
Dynamic: license-file
